{
    "version": 1,
    "license": "CC0-1.0",
    "copyright": "Taken from tgstation at commit https://github.com/tgstation/tgstation/commit/4f6190e2895e09116663ef282d3ce1d8b35c032e | erhardsteinhauer (github): edited sprites for dead and structire-wall states, made structure-2, structure-3 and inhand sprites;",
    "size": {
        "x": 32,
        "y": 32
    },
    "states": [
        {
            "name": "produce"
        },
        {
            "name": "seed"
        },
        {
            "name": "structure-1"
        },
        {
            "name": "structure-2"
        },
        {
            "name": "structure-3"
        },
        {
            "name": "structure-wall-1",
            "directions": 4
        },
        {
            "name": "structure-wall-2",
            "directions": 4
        },
        {
            "name": "structure-wall-3",
            "directions": 4
        },
        {
            "name": "dead"
        },
        {
            "name": "stage-1"
        },
        {
            "name": "stage-2"
        },
        {
            "name": "stage-3"
        },
        {
            "name": "stage-4"
        },
        {
            "name": "harvest"
        },
        {
            "name": "inhand-left",
            "directions": 4
        },
        {
            "name": "inhand-right",
            "directions": 4
        },
        {
            "name": "seed-inhand-left",
            "directions": 4
        },
        {
            "name": "seed-inhand-right",
            "directions": 4
        }
    ]
}