<Document>
  # Argocytes
  
  # Known variants
  ## "Slurva"
  <Box>
  <GuideEntityEmbed Entity="MobArgocyteSlurvaExpeditions"/>
  </Box>
  
  ## "Barrier"
  <Box>
  <GuideEntityEmbed Entity="MobArgocyteBarrierExpeditions"/>
  </Box>
  
  ## "Skitter"
  <Box>
  <GuideEntityEmbed Entity="MobArgocyteSkitterExpeditions"/>
  </Box>
  
  ## "Swiper"
  <Box>
  <GuideEntityEmbed Entity="MobArgocyteSwiperExpeditions"/>
  </Box>
  
  ## "Molder"
  <Box>
  <GuideEntityEmbed Entity="MobArgocyteMolderExpeditions"/>
  </Box>
  
  ## "Pouncer"
  <Box>
  <GuideEntityEmbed Entity="MobArgocytePouncerExpeditions"/>
  </Box>
  
  ## "Glider"
  <Box>
  <GuideEntityEmbed Entity="MobArgocyteGliderExpeditions"/>
  </Box>
  
  ## "Harvester"
  <Box>
  <GuideEntityEmbed Entity="MobArgocyteHarvesterExpeditions"/>
  </Box>
  
  ## "Crawler"
  <Box>
  <GuideEntityEmbed Entity="MobArgocyteCrawlerExpeditions"/>
  </Box>
  
  ## "Enforcer"
  <Box>
  <GuideEntityEmbed Entity="MobArgocyteEnforcerExpeditions"/>
  </Box>
  
  ## "Founder"
  <Box>
  <GuideEntityEmbed Entity="MobArgocyteFounderExpeditions"/>
  </Box>
  
  ## "Leviathing"
  <Box>
  <GuideEntityEmbed Entity="MobArgocyteLeviathingExpeditions"/>
  </Box>
  
  # Missions targets
  ## Elimination
  <Box>
  <GuideEntityEmbed Entity="MobArgocyteLeviathingExpeditions"/>
  </Box>
  Eliminate large and dangerous creature - [color=#a4885c]leviathing[/color] within given time constraints to earn a monetary reward.
  
  ## Destruction
  <Box>
  <GuideEntityEmbed Entity="ArgocyteEgg"/>
  </Box>
  Destroy a certain amount of [color=#a4885c]argocyte eggs[/color] within given time constraints to earn a monetary reward.
</Document>