{
    "version": 1,
    "size": {
        "x": 32,
        "y": 32
    },
    "license": "CC-BY-SA-3.0",
    "copyright": "Felinid sprites made by Adrian16199 (Github), paper and radio sprites by Nikovnik (Github: nkokic); OOC, emote and whispering sprites made by Nesoryo (Discord); radio/ooc/emote/whisper idle states modified from default states by kotobdev (GitHub); emote and ooc sprites modified by Herbtheon (Discord)",
    "states": [
        {
            "name": "felinid0",
            "delays": [
                [
                    0.2,
                    0.3,
                    0.3,
                    0.5
                ]
            ]
        },
        {
            "name": "felinid1"
        },
        {
            "name": "felinid2"
        },
        {
            "name": "paper0",
            "delays": [
                [
                    0.2,
                    0.3,
                    0.3,
                    0.5
                ]
            ]
        },
        {
            "name": "emote0",
            "delays": [
                [
                    0.3,
                    0.2,
                    0.3,
                    0.2
                ]
            ]
        },
        {
            "name": "emote1",
            "delays": [
                [
                    0.5,
                    0.5
                ]
            ]
        },
        {
            "name": "ooc0",
            "delays": [
                [
                    0.2,
                    0.3,
                    0.3,
                    0.5
                ]
            ]
        },
        {
            "name": "ooc1"
        },
        {
            "name": "whisper0",
            "delays": [
                [
                    0.2,
                    0.3,
                    0.3,
                    0.5
                ]
            ]
        },
        {
            "name": "whisper1"
        },
        {
            "name": "radio0",
            "delays": [
                [
                    0.2,
                    0.3,
                    0.3,
                    0.5
                ]
            ]
        },
        {
            "name": "radio1",
            "delays": [
                [
                    0.5,
                    0.5
                ]
            ]
        }
    ]
}
