{
  "version": 1,
  "license": "CC-BY-SA-3.0",
  "copyright": "Based on https://github.com/tgstation/tgstation/blob/master/icons/mob/clothing/eyes.dmi resprited by erhardsteinhauer (discord/github)",
  "size": {
    "x": 32,
    "y": 32
  },
  "states": [
    {
      "name": "base_glasses_01",
      "directions": 4
    },
    {
      "name": "base_glasses_02",
      "directions": 4
    },
    {
      "name": "decor_base_glasses_01",
      "directions": 4
    },
    {
      "name": "decor_base_glasses_02",
      "directions": 4,
	  "delays": [
                [ 0.1, 0.1, 0.8, 0.4 ],
                [ 0.1, 0.1, 0.8, 0.4 ],
                [ 0.1, 0.1, 0.8, 0.4 ],
                [ 0.1, 0.1, 0.8, 0.4 ]
            ]
    }
  ]
}
